{
    "users": [
	{
	    "id": 0,
	    "segment": 0,
	    "profile_image": "https://abs.twimg.com/sticky/default_profile_images/default_profile_normal.png",
	    "display_name": "Unknown user",
	    "handle": "unknown",
	    "flwr_change": "0",
	    "user_state": "Unknown",
	    "past_14_day_tweet_count": "34",
	    "past_14_day_tweet_impression_count": "123",
	    "flwr_followers_added": "0",
	    "flwr_impressions": "9",
	    "advertiser_type": "",
	    "report_date_from": "08/01/2019",
	    "report_date_end": "08/15/2019",
	    "rep_name": "",
	    "rep_email": "",
	    "language": "en",
	    "triggers": []
	},
	{
	    "id": 1,
	    "segment": 1,
	    "profile_image": "https://abs.twimg.com/sticky/default_profile_images/default_profile_normal.png",
	    "display_name": "Active user",
	    "handle": "active",
	    "flwr_change": "55",
	    "user_state": "Active",
	    "past_14_day_tweet_count": "34",
	    "past_14_day_tweet_impression_count": "123",
	    "flwr_followers_added": "105",
	    "flwr_impressions": "95",
	    "advertiser_type": "Active advertiser",
	    "report_date_from": "08/01/2019",
	    "report_date_end": "08/15/2019",
	    "rep_name": "Representative name",
	    "rep_email": "rep@twitter.com",
	    "language": "en",
	    "triggers": ["trigger1", "trigger3", "trigger5"]
	},
	{
	    "id": 2,
	    "segment": 2,
	    "profile_image": "https://abs.twimg.com/sticky/default_profile_images/default_profile_normal.png",
	    "display_name": "Inactive user",
	    "handle": "inactive",
	    "flwr_change": "0",
	    "user_state": "Inactive",
	    "past_14_day_tweet_count": "0",
	    "past_14_day_tweet_impression_count": "0",
	    "flwr_followers_added": "5",
	    "flwr_impressions": "0",
	    "advertiser_type": "Inactive advertiser",
	    "report_date_from": "08/01/2019",
	    "report_date_end": "08/15/2019",
	    "rep_name": "Representative name",
	    "rep_email": "rep@twitter.com",
	    "language": "en",
	    "triggers": ["trigger1", "trigger3", "trigger5"]
	},
	{
	    "id": 3,
	    "segment": 3,
	    "profile_image": "https://abs.twimg.com/sticky/default_profile_images/default_profile_normal.png",
	    "display_name": "Prospect",
	    "handle": "prospect",
	    "flwr_change": "23",
	    "user_state": "Prospect",
	    "past_14_day_tweet_count": "12",
	    "past_14_day_tweet_impression_count": "0",
	    "flwr_followers_added": "4",
	    "flwr_impressions": "0",
	    "advertiser_type": "",
	    "report_date_from": "08/01/2019",
	    "report_date_end": "08/15/2019",
	    "rep_name": "",
	    "rep_email": "",
	    "language": "en",
	    "triggers": []
	},
	{
	    "id": 4,
	    "segment": 3,
	    "profile_image": "https://abs.twimg.com/sticky/default_profile_images/default_profile_normal.png",
	    "display_name": "Prospect Less Tweets",
	    "handle": "prospect",
	    "flwr_change": "23",
	    "user_state": "Prospect",
	    "past_14_day_tweet_count": "-5",
	    "past_14_day_tweet_impression_count": "0",
	    "flwr_followers_added": "4",
	    "flwr_impressions": "0",
	    "advertiser_type": "",
	    "report_date_from": "08/01/2019",
	    "report_date_end": "08/15/2019",
	    "rep_name": "",
	    "rep_email": "",
	    "language": "en",
	    "triggers": []
	},
	{
	    "id": 5,
	    "segment": 3,
	    "profile_image": "https://abs.twimg.com/sticky/default_profile_images/default_profile_normal.png",
	    "display_name": "Prospect Less Impressions",
	    "handle": "prospect",
	    "flwr_change": "23",
	    "user_state": "Prospect",
	    "past_14_day_tweet_count": "12",
	    "past_14_day_tweet_impression_count": "-5",
	    "flwr_followers_added": "4",
	    "flwr_impressions": "0",
	    "advertiser_type": "",
	    "report_date_from": "08/01/2019",
	    "report_date_end": "08/15/2019",
	    "rep_name": "",
	    "rep_email": "",
	    "language": "en",
	    "triggers": []
	}
    ]
}
